sportsbet/__init__.py
sportsbet/__main__.py
sportsbet/cli/__init__.py
sportsbet/cli/_betting.py
sportsbet/cli/_cli.py
sportsbet/cli/_data.py
sportsbet/cli/_options.py
sportsbet/cli/_utils.py
sportsbet/datasets/__init__.py
sportsbet/datasets/_base.py
sportsbet/datasets/_dummy.py
sportsbet/datasets/_soccer/__init__.py
sportsbet/datasets/_soccer/_data.py
sportsbet/datasets/_soccer/_utils.py
sportsbet/evaluation/__init__.py
sportsbet/evaluation/_base.py
sportsbet/evaluation/_classifier.py
sportsbet/evaluation/_model_selection.py
sportsbet/evaluation/_rules.py
sportsbet/gui/.gitignore
sportsbet/gui/app/__init__.py
sportsbet/gui/app/app.py
sportsbet/gui/app/components.py
sportsbet/gui/app/dataloader_creation.py
sportsbet/gui/app/dataloader_loading.py
sportsbet/gui/app/index.py
sportsbet/gui/app/model_creation.py
sportsbet/gui/app/model_loading.py
sportsbet/gui/app/states.py
sportsbet/gui/assets/chakra_color_mode_provider.js
sportsbet/gui/assets/favicon.ico
sportsbet/gui/main.py
sportsbet/gui/requirements.txt
sportsbet/gui/rxconfig.py
sportsbet/py.typed
sports_betting-0.12.1.dist-info/entry_points.txt
sports_betting-0.12.1.dist-info/WHEEL
sports_betting-0.12.1.dist-info/METADATA
sports_betting-0.12.1.dist-info/licenses/LICENSE
sports_betting-0.12.1.dist-info/RECORD
