Metadata-Version: 2.1
Name: sports_betting
Version: 0.12.1
Summary: Python sports betting toolbox.
License: MIT
Author-email: Georgios Douzas <gdouzas@icloud.com>
Requires-Python: >=3.11, <3.13
Classifier: Development Status :: 4 - Beta
Classifier: Intended Audience :: Developers
Classifier: Programming Language :: Python
Classifier: Programming Language :: Python :: 3
Classifier: Programming Language :: Python :: 3 :: Only
Classifier: Programming Language :: Python :: 3.11
Classifier: Programming Language :: Python :: 3.12
Classifier: Topic :: Documentation
Classifier: Topic :: Software Development
Classifier: Topic :: Utilities
Classifier: Typing :: Typed
Requires-Dist: aiohttp>=3.8.4
Requires-Dist: beautifulsoup4>=4.0.0
Requires-Dist: click>=8.1.3
Requires-Dist: cloudpickle>=2.0.0
Requires-Dist: nptyping>=2.5.0
Requires-Dist: pandas>=2.0.0
Requires-Dist: rich>=13.3.3
Requires-Dist: scikit-learn>=1.6.0
Requires-Dist: typing-extensions>=4.5.0
Provides-Extra: gui
Requires-Dist: nest-asyncio>=1.6.0; extra == "gui"
Requires-Dist: reflex==0.7.0; extra == "gui"
Requires-Dist: reflex-ag-grid>=0.0.10; extra == "gui"
Project-URL: Changelog, https://georgedouzas.github.io/sports-betting/changelog
Project-URL: Discussions, https://github.com/georgedouzas/sports-betting/discussions
Project-URL: Documentation, https://georgedouzas.github.io/sports-betting
Project-URL: Funding, https://github.com/sponsors/georgedouzas
Project-URL: Gitter, https://gitter.im/sports-betting/community
Project-URL: Homepage, https://georgedouzas.github.io/sports-betting
Project-URL: Issues, https://github.com/georgedouzas/sports-betting/issues
Project-URL: Repository, https://github.com/georgedouzas/sports-betting
